LICENSE
README.md
setup.py
world_models.egg-info/PKG-INFO
world_models.egg-info/SOURCES.txt
world_models.egg-info/dependency_links.txt
world_models.egg-info/requires.txt
world_models.egg-info/top_level.txt
worldmodels/__init__.py
worldmodels/core/__init__.py
worldmodels/core/base.py
worldmodels/core/chunk.py
worldmodels/core/clock.py
worldmodels/core/driver.py
worldmodels/core/limiters.py
worldmodels/core/random.py
worldmodels/core/replay.py
worldmodels/core/selectors.py
worldmodels/core/streams.py
worldmodels/core/wrappers.py
worldmodels/jax/__init__.py
worldmodels/jax/agent.py
worldmodels/jax/heads.py
worldmodels/jax/internal.py
worldmodels/jax/nets.py
worldmodels/jax/opt.py
worldmodels/jax/outs.py
worldmodels/jax/transform.py
worldmodels/jax/utils.py
worldmodels/run/__init__.py
worldmodels/run/eval_only.py
worldmodels/run/parallel.py
worldmodels/run/pretrain.py
worldmodels/run/train.py
worldmodels/run/train_eval.py