Metadata-Version: 2.1
Name: world-models
Version: 0.2.0
Summary: World models
Home-page: http://github.com/danijar/worldmodels
Author: Danijar Hafner
Author-email: mail@danijar.com
Classifier: Intended Audience :: Science/Research
Classifier: License :: OSI Approved :: MIT License
Classifier: Programming Language :: Python :: 3
Classifier: Topic :: Scientific/Engineering :: Artificial Intelligence
License-File: LICENSE
